{
    "openapi": "3.0.0",
    "info": {
        "title": "Api Seletivo Seplag Gov-MT",
        "version": "0.1"
    },
    "paths": {
        "/api/album": {
            "get": {
                "tags": [
                    "Albuns"
                ],
                "summary": "Todos os Albuns",
                "description": "Lista todos os Albuns",
                "operationId": "7f7a3b4b6ddb653c4e41fac76cc46c75",
                "parameters": [
                    {
                        "name": "page",
                        "in": "query",
                        "description": "Nº da página",
                        "required": false
                    }
                ],
                "responses": {
                    "200": {
                        "description": "OK",
                        "content": {
                            "application/json": {}
                        }
                    }
                },
                "security": [
                    {
                        "bearerAuth": []
                    }
                ]
            },
            "post": {
                "tags": [
                    "Albuns"
                ],
                "summary": "Cadastra novo Album",
                "description": "Registra um novo Album",
                "operationId": "7ef6c3ec7824931c32af2fe12f80514d",
                "parameters": [
                    {
                        "name": "alb_nome",
                        "in": "query",
                        "description": "Nome",
                        "required": true
                    }
                ],
                "responses": {
                    "200": {
                        "description": "OK",
                        "content": {
                            "application/json": {}
                        }
                    },
                    "404": {
                        "description": "Album não encontrado"
                    }
                },
                "security": [
                    {
                        "bearerAuth": []
                    }
                ]
            }
        },
        "/api/album/{alb_id}": {
            "get": {
                "tags": [
                    "Albuns"
                ],
                "summary": "Mostra um Album",
                "description": "Pesquisa por um album através do (alb_id)",
                "operationId": "83a50396f0d1be37d8ef08914a1315b2",
                "parameters": [
                    {
                        "name": "alb_id",
                        "in": "path",
                        "description": "Nº de identificação do album",
                        "required": true,
                        "schema": {
                            "type": "integer",
                            "example": 1
                        }
                    }
                ],
                "responses": {
                    "200": {
                        "description": "Album Encontrado",
                        "content": {
                            "application/json": {}
                        }
                    },
                    "404": {
                        "description": "Album não encontrado"
                    }
                },
                "security": [
                    {
                        "bearerAuth": []
                    }
                ]
            },
            "put": {
                "tags": [
                    "Albuns"
                ],
                "summary": "Atualizar dados de um Album",
                "description": "Editar os dados de um album através do (alb_id)",
                "operationId": "6c207874928b77946b8a90987c7bb99b",
                "requestBody": {
                    "required": true,
                    "content": {
                        "application/json": {
                            "schema": {
                                "required": [
                                    "alb_id",
                                    "alb_nome"
                                ],
                                "properties": {
                                    "alb_id": {
                                        "type": "integer",
                                        "example": "1"
                                    },
                                    "alb_nome": {
                                        "type": "string",
                                        "example": "Nome album"
                                    }
                                },
                                "type": "object"
                            }
                        }
                    }
                },
                "responses": {
                    "200": {
                        "description": "Album atualizado com sucesso",
                        "content": {
                            "application/json": {
                                "schema": {
                                    "properties": {
                                        "message": {
                                            "type": "string",
                                            "example": "Albumn atualizado com sucesso"
                                        }
                                    },
                                    "type": "object"
                                }
                            }
                        }
                    }
                }
            },
            "delete": {
                "tags": [
                    "Albuns"
                ],
                "summary": "Exclui um Album",
                "description": "Exclui um album através do (alb_id)",
                "operationId": "05cbfe7da6ab3aa0cc58363bed3cf16e",
                "parameters": [
                    {
                        "name": "alb_id",
                        "in": "path",
                        "description": "ID do album",
                        "required": true,
                        "schema": {
                            "type": "integer",
                            "example": 1
                        }
                    }
                ],
                "responses": {
                    "200": {
                        "description": "Album excluído com sucesso",
                        "content": {
                            "application/json": {}
                        }
                    },
                    "404": {
                        "description": "Não foi possível excluir o album"
                    }
                },
                "security": [
                    {
                        "bearerAuth": []
                    }
                ]
            }
        },
        "/api/artistaalbum": {
            "post": {
                "tags": [
                    "Artistas Albuns"
                ],
                "summary": "Cadastra vinculo de Artista com album",
                "description": "Registra o album de um artista",
                "operationId": "a23623e6b037ed5e790505568ed30b73",
                "parameters": [
                    {
                        "name": "art_id",
                        "in": "query",
                        "description": "Nº identificação do artista",
                        "required": true
                    },
                    {
                        "name": "alb_id",
                        "in": "query",
                        "description": "Nº identificação do Album",
                        "required": true
                    }
                ],
                "responses": {
                    "200": {
                        "description": "OK",
                        "content": {
                            "application/json": {}
                        }
                    },
                    "404": {
                        "description": "Erro"
                    }
                },
                "security": [
                    {
                        "bearerAuth": []
                    }
                ]
            }
        },
        "/api/artista": {
            "get": {
                "tags": [
                    "Artistas"
                ],
                "summary": "Todos os Artistas",
                "description": "Lista todos os Artistas com seus albuns",
                "operationId": "415b1f39080db3f4e460e2418e0f6cfa",
                "parameters": [
                    {
                        "name": "page",
                        "in": "query",
                        "description": "Nº da página",
                        "required": false
                    }
                ],
                "responses": {
                    "200": {
                        "description": "OK",
                        "content": {
                            "application/json": {}
                        }
                    }
                },
                "security": [
                    {
                        "bearerAuth": []
                    }
                ]
            },
            "post": {
                "tags": [
                    "Artistas"
                ],
                "summary": "Cadastra novo Artista",
                "description": "Registra um novo Artista",
                "operationId": "cc47ff4349a86cabe02cf497c6d42539",
                "parameters": [
                    {
                        "name": "art_nome",
                        "in": "query",
                        "description": "Nome",
                        "required": true
                    }
                ],
                "responses": {
                    "200": {
                        "description": "OK",
                        "content": {
                            "application/json": {}
                        }
                    },
                    "404": {
                        "description": "Artista não encontrado"
                    }
                },
                "security": [
                    {
                        "bearerAuth": []
                    }
                ]
            }
        },
        "/api/artista/{art_id}": {
            "get": {
                "tags": [
                    "Artistas"
                ],
                "summary": "Mostra um Artista",
                "description": "Pesquisa por um artista através do (art_id)",
                "operationId": "6274b9b0e8feb7607f9b2f2fd65b34e1",
                "parameters": [
                    {
                        "name": "art_id",
                        "in": "path",
                        "description": "Nº de identificação do artista",
                        "required": true,
                        "schema": {
                            "type": "integer",
                            "example": 1
                        }
                    }
                ],
                "responses": {
                    "200": {
                        "description": "Artista Encontrado",
                        "content": {
                            "application/json": {}
                        }
                    },
                    "404": {
                        "description": "Pessoa não encontrada"
                    }
                },
                "security": [
                    {
                        "bearerAuth": []
                    }
                ]
            },
            "put": {
                "tags": [
                    "Artistas"
                ],
                "summary": "Atualizar dados de um Artista",
                "description": "Editar os dados de um artista através do (art_id)",
                "operationId": "62a8a7197054b24812dea4c4bade88b4",
                "requestBody": {
                    "required": true,
                    "content": {
                        "application/json": {
                            "schema": {
                                "required": [
                                    "art_id",
                                    "art_nome"
                                ],
                                "properties": {
                                    "art_id": {
                                        "type": "integer",
                                        "example": "1"
                                    },
                                    "art_nome": {
                                        "type": "string",
                                        "example": "Nome artista"
                                    }
                                },
                                "type": "object"
                            }
                        }
                    }
                },
                "responses": {
                    "200": {
                        "description": "Artista atualizado com sucesso",
                        "content": {
                            "application/json": {
                                "schema": {
                                    "properties": {
                                        "message": {
                                            "type": "string",
                                            "example": "Endereço atualizado com sucesso"
                                        },
                                        "artista": {
                                            "properties": {
                                                "art_nome": {
                                                    "type": "string",
                                                    "example": "Nome Artista"
                                                }
                                            },
                                            "type": "object"
                                        }
                                    },
                                    "type": "object"
                                }
                            }
                        }
                    },
                    "400": {
                        "description": "Requisição inválida"
                    },
                    "404": {
                        "description": "Endereco não encontrado"
                    }
                },
                "security": [
                    {
                        "bearerAuth": []
                    }
                ]
            },
            "delete": {
                "tags": [
                    "Artistas"
                ],
                "summary": "Exclui um Artista",
                "description": "Exclui um artista através do (art_id)",
                "operationId": "231dc0c88fd150916006c00ef034ac4b",
                "parameters": [
                    {
                        "name": "art_id",
                        "in": "path",
                        "description": "ID do artista",
                        "required": true,
                        "schema": {
                            "type": "integer",
                            "example": 1
                        }
                    }
                ],
                "responses": {
                    "200": {
                        "description": "Artista excluído com sucesso",
                        "content": {
                            "application/json": {}
                        }
                    },
                    "404": {
                        "description": "Não foi possível excluir a pessoa"
                    }
                },
                "security": [
                    {
                        "bearerAuth": []
                    }
                ]
            }
        },
        "/api/login": {
            "post": {
                "tags": [
                    "Autenticação"
                ],
                "summary": "Autenticar usuário",
                "operationId": "a3b306d14572d1f4bd6c064b3233e7b8",
                "parameters": [
                    {
                        "name": "email",
                        "in": "query",
                        "description": "Informe o email",
                        "required": true,
                        "schema": {
                            "type": "string"
                        },
                        "example": "teste@seplag.mt.gov.br"
                    },
                    {
                        "name": "password",
                        "in": "query",
                        "description": "Insira a senha",
                        "required": true,
                        "schema": {
                            "type": "string"
                        },
                        "example": "seplag2026"
                    }
                ],
                "responses": {
                    "200": {
                        "description": "Successo no Login"
                    },
                    "401": {
                        "description": "Credenciais inválidas"
                    }
                }
            }
        },
        "/api/refresh": {
            "post": {
                "tags": [
                    "Autenticação"
                ],
                "summary": "Renovar Token",
                "operationId": "2c27d311a2876560fcb5a754b556cdc5",
                "parameters": [
                    {
                        "name": "email",
                        "in": "query",
                        "description": "Informe um email",
                        "required": true,
                        "schema": {
                            "type": "string"
                        },
                        "example": "teste@seplag.mt.gov.br"
                    },
                    {
                        "name": "password",
                        "in": "query",
                        "description": "Insira a senha",
                        "required": true,
                        "schema": {
                            "type": "string"
                        },
                        "example": "seplag2026"
                    }
                ],
                "responses": {
                    "200": {
                        "description": "Successo no Refresh"
                    },
                    "401": {
                        "description": "Credenciais inválidas"
                    }
                }
            }
        },
        "/api/foto-album": {
            "post": {
                "tags": [
                    "Foto Upload"
                ],
                "summary": "Faz o upload de uma foto de album",
                "description": "Upload de Arquivo",
                "operationId": "665617137aa8a9d1c360a2ea91d98dc9",
                "parameters": [
                    {
                        "name": "art_id",
                        "in": "query",
                        "description": "Nº de identificação do Artista",
                        "required": true
                    }
                ],
                "requestBody": {
                    "required": true,
                    "content": {
                        "multipart/form-data": {
                            "schema": {
                                "properties": {
                                    "file": {
                                        "type": "string",
                                        "format": "binary"
                                    }
                                },
                                "type": "object"
                            }
                        }
                    }
                },
                "responses": {
                    "200": {
                        "description": "Arquivo enviado com sucesso",
                        "content": {
                            "application/json": {
                                "schema": {
                                    "properties": {
                                        "success": {
                                            "type": "boolean"
                                        },
                                        "message": {
                                            "type": "string"
                                        },
                                        "file": {
                                            "type": "string"
                                        }
                                    },
                                    "type": "object"
                                }
                            }
                        }
                    },
                    "400": {
                        "description": "Erro no upload"
                    }
                },
                "security": [
                    {
                        "bearerAuth": []
                    }
                ]
            }
        },
        "/api/musica": {
            "get": {
                "tags": [
                    "Musicas"
                ],
                "summary": "Todas as Musicas",
                "description": "Lista todas as Musicas",
                "operationId": "01de9509d3e6ccaa97ce184616faba9b",
                "parameters": [
                    {
                        "name": "page",
                        "in": "query",
                        "description": "Nº da página",
                        "required": false
                    }
                ],
                "responses": {
                    "200": {
                        "description": "OK",
                        "content": {
                            "application/json": {}
                        }
                    }
                },
                "security": [
                    {
                        "bearerAuth": []
                    }
                ]
            },
            "post": {
                "tags": [
                    "Musicas"
                ],
                "summary": "Cadastra nova Musica",
                "description": "Registra uma nova Musica",
                "operationId": "c703a59db1ae0961c25ba18b8721f70c",
                "parameters": [
                    {
                        "name": "mus_titulo",
                        "in": "query",
                        "description": "Titulo da Musica",
                        "required": true
                    }
                ],
                "responses": {
                    "200": {
                        "description": "OK",
                        "content": {
                            "application/json": {}
                        }
                    },
                    "404": {
                        "description": "Musica não encontrada"
                    }
                },
                "security": [
                    {
                        "bearerAuth": []
                    }
                ]
            }
        },
        "/api/musica/{mus_id}": {
            "get": {
                "tags": [
                    "Musicas"
                ],
                "summary": "Mostra uma Musica",
                "description": "Pesquisa por uma musica através do (mus_id)",
                "operationId": "65f4e789c3b27a581647d0747baad355",
                "parameters": [
                    {
                        "name": "mus_id",
                        "in": "path",
                        "description": "Nº de identificação da musica",
                        "required": true,
                        "schema": {
                            "type": "integer",
                            "example": 1
                        }
                    }
                ],
                "responses": {
                    "200": {
                        "description": "Musica Encontrada",
                        "content": {
                            "application/json": {}
                        }
                    },
                    "404": {
                        "description": "Musica não encontrada"
                    }
                },
                "security": [
                    {
                        "bearerAuth": []
                    }
                ]
            },
            "put": {
                "tags": [
                    "Musicas"
                ],
                "summary": "Atualizar dados de uma Musica",
                "description": "Editar os dados de uma musica através do (mus_id)",
                "operationId": "630d09f9d4e6cb123573694078f4a078",
                "requestBody": {
                    "required": true,
                    "content": {
                        "application/json": {
                            "schema": {
                                "required": [
                                    "mus_id",
                                    "mus_titulo"
                                ],
                                "properties": {
                                    "mus_id": {
                                        "type": "integer",
                                        "example": "1"
                                    },
                                    "mus_titulo": {
                                        "type": "string",
                                        "example": "Nome musica"
                                    }
                                },
                                "type": "object"
                            }
                        }
                    }
                },
                "responses": {
                    "200": {
                        "description": "Musica atualizado com sucesso",
                        "content": {
                            "application/json": {
                                "schema": {
                                    "properties": {
                                        "message": {
                                            "type": "string",
                                            "example": "Musica atualizado com sucesso"
                                        }
                                    },
                                    "type": "object"
                                }
                            }
                        }
                    }
                }
            },
            "delete": {
                "tags": [
                    "Musicas"
                ],
                "summary": "Exclui uma Musica",
                "description": "Exclui uma musica através do (mus_id)",
                "operationId": "9cc191355d78db8b48ee779129367239",
                "parameters": [
                    {
                        "name": "mus_id",
                        "in": "path",
                        "description": "ID do musica",
                        "required": true,
                        "schema": {
                            "type": "integer",
                            "example": 1
                        }
                    }
                ],
                "responses": {
                    "200": {
                        "description": "musica excluído com sucesso",
                        "content": {
                            "application/json": {}
                        }
                    },
                    "404": {
                        "description": "Não foi possível excluir a musica",
                        "content": {
                            "application/json": {}
                        }
                    }
                },
                "security": [
                    {
                        "bearerAuth": []
                    }
                ]
            }
        },
        "/api/regional": {
            "get": {
                "tags": [
                    "Regionais"
                ],
                "summary": "Todos as Unidades Regionais",
                "description": "Lista todos as Unidade Regionais",
                "operationId": "49685f8deed49afcb9948e7f3cdeb746",
                "parameters": [
                    {
                        "name": "page",
                        "in": "query",
                        "description": "Nº da página",
                        "required": false
                    }
                ],
                "responses": {
                    "200": {
                        "description": "OK",
                        "content": {
                            "application/json": {}
                        }
                    }
                },
                "security": [
                    {
                        "bearerAuth": []
                    }
                ]
            }
        }
    },
    "components": {
        "responses": {
            "400": {
                "description": "Endereco não encontrado"
            },
            "404": {
                "description": "Musica não encontrado"
            }
        },
        "securitySchemes": {
            "bearerAuth": {
                "type": "http",
                "bearerFormat": "JWT",
                "scheme": "bearer"
            }
        }
    },
    "tags": [
        {
            "name": "Albuns",
            "description": "Albuns"
        },
        {
            "name": "Artistas Albuns",
            "description": "Artistas Albuns"
        },
        {
            "name": "Artistas",
            "description": "Artistas"
        },
        {
            "name": "Autenticação",
            "description": "Autenticação"
        },
        {
            "name": "Foto Upload",
            "description": "Foto Upload"
        },
        {
            "name": "Musicas",
            "description": "Musicas"
        },
        {
            "name": "Regionais",
            "description": "Regionais"
        }
    ]
}